__init__.py
criador_nomes.py
NameCreator_EricFerreira-0.0.3.dist-info/METADATA
NameCreator_EricFerreira-0.0.3.dist-info/WHEEL
NameCreator_EricFerreira-0.0.3.dist-info/top_level.txt
NameCreator_EricFerreira-0.0.3.dist-info/RECORD
