Metadata-Version: 2.1
Name: NameCreator-EricFerreira
Version: 0.0.3
Summary: A name creator package only for tests of Continuous Delivery
Author-email: Eric Ferreira <eric_fpereira@hotmail.com>
Project-URL: Homepage, https://github.com/ericfp87/teste_trabalho_devops
Project-URL: Bug Tracker, https://github.com/pypa/sampleproject/issues
Classifier: Programming Language :: Python :: 3
Classifier: License :: OSI Approved :: MIT License
Classifier: Operating System :: OS Independent
Requires-Python: >=3.9
